trace_time/__init__.py
trace_time/timer.py
trace_time/tests/__init__.py
trace_time/tests/test_timer.py
trace_time_glaiel-0.0.3.dist-info/LICENSE
trace_time_glaiel-0.0.3.dist-info/METADATA
trace_time_glaiel-0.0.3.dist-info/WHEEL
trace_time_glaiel-0.0.3.dist-info/top_level.txt
trace_time_glaiel-0.0.3.dist-info/RECORD
