Metadata-Version: 2.1
Name: trace-time-glaiel
Version: 0.0.3
Summary: A package providing timer tools
Home-page: https://github.com/glaiel/trace_time
Author: glaiel
License: UNKNOWN
Platform: UNKNOWN
Classifier: Programming Language :: Python :: 3
Classifier: License :: OSI Approved :: MIT License
Classifier: Operating System :: OS Independent
Classifier: Development Status :: 2 - Pre-Alpha
Requires-Python: >=3.6
